{
  "unversionedId": "hasura-cloud/projects/details",
  "id": "hasura-cloud/projects/details",
  "title": "Cloud: Project Details",
  "description": "Project Details on Hasura Cloud",
  "source": "@site/docs/hasura-cloud/projects/details.mdx",
  "sourceDirName": "hasura-cloud/projects",
  "slug": "/hasura-cloud/projects/details",
  "permalink": "/docs/latest/hasura-cloud/projects/details",
  "draft": false,
  "editUrl": "https://github.com/hasura/graphql-engine/edit/master/docs/docs/hasura-cloud/projects/details.mdx",
  "tags": [],
  "version": "current",
  "sidebarPosition": 2,
  "frontMatter": {
    "description": "Project Details on Hasura Cloud",
    "title": "Cloud: Project Details",
    "keywords": [
      "hasura",
      "docs",
      "cloud",
      "rename",
      "labels",
      "details",
      "region"
    ],
    "sidebar_label": "Project details",
    "sidebar_position": 2
  },
  "sidebar": "docsSidebar",
  "previous": {
    "title": "Create Projects",
    "permalink": "/docs/latest/hasura-cloud/projects/create"
  },
  "next": {
    "title": "Project collaborators",
    "permalink": "/docs/latest/hasura-cloud/projects/collaborators"
  }
}